peitho_data/Ubuntu-B.ttf
peitho_data/__init__.py
peitho_data/trello_api.py
peitho_data/word_cloud.py
peitho_data/datafication/__init__.py
peitho_data/datafication/epub.py
peitho_data/graph/__init__.py
peitho_data/graph/knowledge_graph_spec.py
peitho_data/machine_learning/__init__.py
peitho_data/machine_learning/concept_learning.py
peitho_data/machine_learning/cnn/__init__.py
peitho_data/machine_learning/cnn/image_convolution.py
peitho_data/tests/__init__.py
peitho_data/tests/test_trello_api.py
peitho_data/tests/test_word_cloud.py
peitho_data/tests/datafication/__init__.py
peitho_data/tests/datafication/test_epub.py
peitho_data/tests/graph/__init__.py
peitho_data/tests/graph/test_knowledge_graph_spec.py
peitho_data/tests/machine_learning/__init__.py
peitho_data/tests/machine_learning/test_concept_learning.py
peitho_data/tests/machine_learning/cnn/__init__.py
peitho_data/tests/machine_learning/cnn/test_image_convolution.py
peitho_data-2.3.15.dist-info/LICENSE
peitho_data-2.3.15.dist-info/METADATA
peitho_data-2.3.15.dist-info/WHEEL
peitho_data-2.3.15.dist-info/top_level.txt
peitho_data-2.3.15.dist-info/RECORD
