Metadata-Version: 2.1
Name: peitho-data
Version: 2.3.15
Summary: An opinionated Python package on Big Data Analytics
Home-page: https://github.com/QubitPi/peitho-data
Author: Jiaqi liu
Author-email: Jiaqi liu <jack20220723@gmail.com>
License: Apache-2.0
Project-URL: Homepage, https://github.com/QubitPi/peitho-data
Project-URL: Bug Tracker, https://github.com/QubitPi/peitho-data/issues
Requires-Python: >=3.10
License-File: LICENSE
Requires-Dist: bs4
Requires-Dist: opencv-python
Requires-Dist: numpy
Requires-Dist: wordcloud
Requires-Dist: pycodestyle
Requires-Dist: requests
Requires-Dist: sphinx-rtd-theme
Requires-Dist: matplotlib
Requires-Dist: ebooklib
Requires-Dist: requests-mock
